postdown
