Metadata-Version: 1.0
Name: Postdown
Version: 1.0.10
Summary: Generate markdown API document from Postman.
Home-page: https://github.com/TitorX/Postdown
Author: Titor
Author-email: sun.qd.china@outlook.com
License: UNKNOWN
Platform: UNKNOWN
